starexx/__init__.py
starexx/core.py
starexx/secondary.py
starexx-2.0.2.dist-info/licenses/LICENSE
starexx-2.0.2.dist-info/METADATA
starexx-2.0.2.dist-info/WHEEL
starexx-2.0.2.dist-info/top_level.txt
starexx-2.0.2.dist-info/RECORD
