Metadata-Version: 2.4
Name: starexx
Version: 2.0.2
Summary: Beginner-Friendly syntax python module
Home-page: https://realstarexx.github.io/docs
Author: Ankit Mehta
Author-email: starexx.m@gmail.com
Classifier: Programming Language :: Python :: 3
Classifier: License :: OSI Approved :: MIT License
Classifier: Operating System :: OS Independent
Requires-Python: >=3.6
License-File: LICENSE
Dynamic: author
Dynamic: author-email
Dynamic: classifier
Dynamic: description
Dynamic: description-content-type
Dynamic: home-page
Dynamic: license-file
Dynamic: requires-python
Dynamic: summary
